{"nodes": [{"id": "altium_job1_pcb", "label": "PCB Layout Render (Job1)", "file_type": "image", "source_file": "Altium/Job1.jpg", "source_location": null, "source_url": null, "captured_at": null, "author": null, "contributor": null}, {"id": "altium_job1_pcb_module", "label": "ESP32 Module Footprint", "file_type": "concept", "source_file": "Altium/Job1.jpg", "source_location": null, "source_url": null, "captured_at": null, "author": null, "contributor": null}, {"id": "altium_job1_pcb_sn74", "label": "SN74LVC2G14 Footprint (PA SN74LVC2G14 1-6)", "file_type": "concept", "source_file": "Altium/Job1.jpg", "source_location": null, "source_url": null, "captured_at": null, "author": null, "contributor": null}, {"id": "altium_job1_pcb_pir", "label": "PIR Connector (PA PIR 0-3)", "file_type": "concept", "source_file": "Altium/Job1.jpg", "source_location": null, "source_url": null, "captured_at": null, "author": null, "contributor": null}, {"id": "altium_job1_pcb_led", "label": "LED102 Connector (PA LED102 0-2)", "file_type": "concept", "source_file": "Altium/Job1.jpg", "source_location": null, "source_url": null, "captured_at": null, "author": null, "contributor": null}, {"id": "altium_job1_pcb_power", "label": "Power Connector (PA Power 0-2)", "file_type": "concept", "source_file": "Altium/Job1.jpg", "source_location": null, "source_url": null, "captured_at": null, "author": null, "contributor": null}, {"id": "altium_job1_pcb_button", "label": "Button Connector (PA Button 0-2)", "file_type": "concept", "source_file": "Altium/Job1.jpg", "source_location": null, "source_url": null, "captured_at": null, "author": null, "contributor": null}, {"id": "altium_job1_pcb_resistor_array", "label": "Resistor Arrays (R1-R4, CO R1-R4)", "file_type": "concept", "source_file": "Altium/Job1.jpg", "source_location": null, "source_url": null, "captured_at": null, "author": null, "contributor": null}], "edges": [{"source": "altium_job1_pcb", "target": "altium_job1_pcb_module", "relation": "references", "confidence": "EXTRACTED", "confidence_score": 1.0, "source_file": "Altium/Job1.jpg", "source_location": null, "weight": 1.0}, {"source": "altium_job1_pcb", "target": "altium_job1_pcb_sn74", "relation": "references", "confidence": "EXTRACTED", "confidence_score": 1.0, "source_file": "Altium/Job1.jpg", "source_location": null, "weight": 1.0}, {"source": "altium_job1_pcb", "target": "altium_job1_pcb_pir", "relation": "references", "confidence": "EXTRACTED", "confidence_score": 1.0, "source_file": "Altium/Job1.jpg", "source_location": null, "weight": 1.0}, {"source": "altium_job1_pcb", "target": "altium_job1_pcb_led", "relation": "references", "confidence": "EXTRACTED", "confidence_score": 1.0, "source_file": "Altium/Job1.jpg", "source_location": null, "weight": 1.0}, {"source": "altium_job1_pcb", "target": "altium_job1_pcb_power", "relation": "references", "confidence": "EXTRACTED", "confidence_score": 1.0, "source_file": "Altium/Job1.jpg", "source_location": null, "weight": 1.0}, {"source": "altium_job1_pcb", "target": "altium_job1_pcb_button", "relation": "references", "confidence": "EXTRACTED", "confidence_score": 1.0, "source_file": "Altium/Job1.jpg", "source_location": null, "weight": 1.0}, {"source": "altium_job1_pcb", "target": "altium_job1_pcb_resistor_array", "relation": "references", "confidence": "EXTRACTED", "confidence_score": 1.0, "source_file": "Altium/Job1.jpg", "source_location": null, "weight": 1.0}, {"source": "altium_job1_pcb_module", "target": "readme_esp32_s3_zero", "relation": "semantically_similar_to", "confidence": "INFERRED", "confidence_score": 0.95, "source_file": "Altium/Job1.jpg", "source_location": null, "weight": 1.0}, {"source": "altium_job1_pcb_sn74", "target": "readme_sn74lvc2g14", "relation": "semantically_similar_to", "confidence": "INFERRED", "confidence_score": 0.95, "source_file": "Altium/Job1.jpg", "source_location": null, "weight": 1.0}, {"source": "altium_job1_pcb_pir", "target": "readme_pir_sensor", "relation": "semantically_similar_to", "confidence": "INFERRED", "confidence_score": 0.95, "source_file": "Altium/Job1.jpg", "source_location": null, "weight": 1.0}, {"source": "altium_job1_pcb_led", "target": "readme_sk6812_rgbw", "relation": "semantically_similar_to", "confidence": "INFERRED", "confidence_score": 0.85, "source_file": "Altium/Job1.jpg", "source_location": null, "weight": 1.0}, {"source": "altium_job1_pcb_button", "target": "readme_hardware_button", "relation": "semantically_similar_to", "confidence": "INFERRED", "confidence_score": 0.95, "source_file": "Altium/Job1.jpg", "source_location": null, "weight": 1.0}, {"source": "altium_job1_pcb", "target": "altium_led_mirror_address_project_outputs_for_led_mirror_address_job1", "relation": "references", "confidence": "EXTRACTED", "confidence_score": 1.0, "source_file": "Altium/Job1.jpg", "source_location": null, "weight": 1.0}], "hyperedges": []}